paytmpg/VERSION.ini
paytmpg/VERSION.py
paytmpg/__init__.py
paytmpg/merchant/__init__.py
paytmpg/merchant/models/PaymentDetail.py
paytmpg/merchant/models/PaymentStatusDetail.py
paytmpg/merchant/models/RefundDetail.py
paytmpg/merchant/models/RefundStatusDetail.py
paytmpg/merchant/models/SDKResponse.py
paytmpg/merchant/models/Time.py
paytmpg/merchant/models/__init__.py
paytmpg/pg/Payment.py
paytmpg/pg/Refund.py
paytmpg/pg/Request.py
paytmpg/pg/SDKException.py
paytmpg/pg/__init__.py
paytmpg/pg/constants/ErrorConstants.py
paytmpg/pg/constants/LibraryConstants.py
paytmpg/pg/constants/MerchantProperty.py
paytmpg/pg/constants/__init__.py
paytmpg/pg/enums/EChannelId.py
paytmpg/pg/enums/EnumCurrency.py
paytmpg/pg/enums/UserSubWalletType.py
paytmpg/pg/enums/__init__.py
paytmpg/pg/models/ExtendInfo.py
paytmpg/pg/models/GoodsInfo.py
paytmpg/pg/models/Money.py
paytmpg/pg/models/PaymentMode.py
paytmpg/pg/models/ShippingInfo.py
paytmpg/pg/models/UserInfo.py
paytmpg/pg/models/__init__.py
paytmpg/pg/request/BaseHeader.py
paytmpg/pg/request/ExtraParameterMap.py
paytmpg/pg/request/InitiateTransactionRequest.py
paytmpg/pg/request/InitiateTransactionRequestBody.py
paytmpg/pg/request/NativePaymentStatusRequest.py
paytmpg/pg/request/NativePaymentStatusRequestBody.py
paytmpg/pg/request/NativeRefundStatusRequest.py
paytmpg/pg/request/NativeRefundStatusRequestBody.py
paytmpg/pg/request/RefundBaseRequest.py
paytmpg/pg/request/RefundBaseRquest.py
paytmpg/pg/request/RefundInitiateRequest.py
paytmpg/pg/request/RefundInitiateRequestBody.py
paytmpg/pg/request/RequestHeader.py
paytmpg/pg/request/SecureRequestHeader.py
paytmpg/pg/request/__init__.py
paytmpg/pg/response/AsyncRefundResponse.py
paytmpg/pg/response/AsyncRefundResponseBody.py
paytmpg/pg/response/BaseResponseBody.py
paytmpg/pg/response/ChildTransaction.py
paytmpg/pg/response/InitiateTransactionResponse.py
paytmpg/pg/response/InitiateTransactionResponseBody.py
paytmpg/pg/response/NativePaymentStatusResponse.py
paytm_pg-1.0.9.dist-info/METADATA
paytm_pg-1.0.9.dist-info/WHEEL
paytm_pg-1.0.9.dist-info/top_level.txt
paytm_pg-1.0.9.dist-info/RECORD
